todo/__init__.py
todo/app.py
todo/main.py
todo/models.py
todo/storage.py
todo/widgets.py
silo_todo-0.1.0.dist-info/METADATA
silo_todo-0.1.0.dist-info/WHEEL
silo_todo-0.1.0.dist-info/entry_points.txt
silo_todo-0.1.0.dist-info/licenses/LICENSE
silo_todo-0.1.0.dist-info/RECORD
