Metadata-Version: 2.1
Name: silo-todo
Version: 0.1.0
Summary: A beautiful terminal-based todo list with vim-style navigation, workspaces, and priorities
Project-URL: Homepage, https://github.com/fashton/silo-todo
Project-URL: Repository, https://github.com/fashton/silo-todo
Author: fashton
License: MIT
License-File: LICENSE
Keywords: cli,productivity,terminal,textual,todo,tui,vim,workspace
Classifier: Development Status :: 4 - Beta
Classifier: Environment :: Console
Classifier: Intended Audience :: Developers
Classifier: Intended Audience :: End Users/Desktop
Classifier: License :: OSI Approved :: MIT License
Classifier: Operating System :: OS Independent
Classifier: Programming Language :: Python :: 3
Classifier: Programming Language :: Python :: 3.10
Classifier: Programming Language :: Python :: 3.11
Classifier: Programming Language :: Python :: 3.12
Classifier: Topic :: Utilities
Requires-Python: >=3.10
Requires-Dist: textual>=0.45.0
Requires-Dist: typer[all]>=0.9.0
